wogDev/CurrencyRGame.py
wogDev/Factory.py
wogDev/GuessGame.py
wogDev/MemoryGame.py
wogDev/__init__.py
wogDev/mainGame.py
wogDev/utils.py
wogDev/wog_abs.py
wogDev-1.1.3.dist-info/LICENSE.txt
wogDev-1.1.3.dist-info/METADATA
wogDev-1.1.3.dist-info/WHEEL
wogDev-1.1.3.dist-info/top_level.txt
wogDev-1.1.3.dist-info/RECORD
