Metadata-Version: 2.1
Name: wogDev
Version: 1.1.3
Summary: World of Games
Home-page: UNKNOWN
Author: Oren Jacobovitz
Author-email: oj.gmbox@gmail.com
License: Apache License 2.0
Platform: UNKNOWN
